[
 {
  "id": "1699963321841",
  "value": "Literal",
  "label": "Title",
  "type": "Textbox",
  "disambiguate": "True",
  "property": "http://purl.org/dc/terms/title",
  "prepend": "The title of the data service, generally taken from the webpage.",
  "placeholder": "Data Service title",
  "browse": "False",
  "searchWikidata": "False",
  "searchVocab": "False",
  "searchGeonames": "False",
  "url": "False",
  "vocab": [],
  "disabled": "False",
  "class": "col-md-11",
  "cache_autocomplete": "off"
 },
 {
  "id": "1699963337790",
  "property": "http://purl.org/dc/terms/description",
  "placeholder": "Data Service description",
  "prepend": "A summary of what users can do with the data service.",
  "value": "Literal",
  "label": "Description",
  "type": "Textbox",
  "disambiguate": "False",
  "browse": "False",
  "searchWikidata": "False",
  "searchVocab": "False",
  "searchGeonames": "False",
  "url": "False",
  "vocab": [],
  "disabled": "False",
  "class": "col-md-11",
  "cache_autocomplete": "off"
 },
 {
  "id": "1699963389130",
  "type": "Textbox",
  "value": "URL",
  "prepend": "The primary location of the service.",
  "property": "http://www.w3.org/ns/dcat#endpointURL",
  "label": "Access URL",
  "placeholder": "URL",
  "disambiguate": "False",
  "browse": "False",
  "searchWikidata": "False",
  "searchVocab": "False",
  "searchGeonames": "False",
  "url": "True",
  "vocab": [],
  "disabled": "False",
  "class": "col-md-11",
  "cache_autocomplete": "off"
 },
 {
  "id": "1699963401717",
  "prepend": "A web page that gives a description of the services available including their operations, parameters etc.",
  "property": "http://www.w3.org/ns/dcat#endpointDescription",
  "type": "Textbox",
  "placeholder": "URL",
  "value": "URL",
  "label": "Additional Information",
  "disambiguate": "False",
  "browse": "False",
  "searchWikidata": "False",
  "searchVocab": "False",
  "searchGeonames": "False",
  "url": "True",
  "vocab": [],
  "disabled": "False",
  "class": "col-md-11",
  "cache_autocomplete": "off"
 },
 {
  "id": "1699963421911",
  "type": "Textbox",
  "property": "http://purl.org/dc/terms/type",
  "placeholder": "Digital Platform",
  "value": "URI",
  "prepend": "The type of data service, based on the KNOT Taxonomy.",
  "label": "Type",
  "browse": "True",
  "disambiguate": "False",
  "searchWikidata": "True",
  "searchVocab": "False",
  "searchGeonames": "False",
  "url": "False",
  "vocab": [],
  "disabled": "False",
  "class": "col-md-11",
  "cache_autocomplete": "off"
 },
 {
  "id": "1699963442452",
  "prepend": "The type of digital research activities users can engage in via the service, based on Tadirah.",
  "placeholder": "Analysis",
  "type": "Textbox",
  "label": "Research Activities for Users",
  "value": "URI",
  "property": "http://www.w3.org/ns/dcat#theme",
  "browse": "True",
  "disambiguate": "False",
  "searchWikidata": "True",
  "searchVocab": "False",
  "searchGeonames": "False",
  "url": "False",
  "vocab": [],
  "disabled": "False",
  "class": "col-md-11",
  "cache_autocomplete": "off"
 },
 {
  "id": "1699963525827",
  "label": "License",
  "value": "URI",
  "type": "Textbox",
  "property": "http://purl.org/dc/terms/license",
  "prepend": "The license(s) under which the service or its elements are available.",
  "placeholder": "CC-BY-NC",
  "disambiguate": "False",
  "browse": "False",
  "searchWikidata": "True",
  "searchVocab": "False",
  "searchGeonames": "False",
  "url": "False",
  "vocab": [],
  "disabled": "False",
  "class": "col-md-11",
  "cache_autocomplete": "off"
 },
 {
  "id": "1700064981690",
  "label": "Uses Dataset",
  "prepend": "The dataset that the service makes available.",
  "property": "http://www.w3.org/ns/dcat#servesDataset",
  "value": "URI",
  "type": "Textbox",
  "placeholder": "",
  "disambiguate": "False",
  "browse": "False",
  "searchWikidata": "True",
  "searchVocab": "False",
  "searchGeonames": "False",
  "url": "False",
  "vocab": [],
  "disabled": "False",
  "class": "col-md-11",
  "cache_autocomplete": "off"
 }
]